wsimple/__init__.py
wsimple/api/__init__.py
wsimple/api/api.py
wsimple/api/endpoints.py
wsimple/api/errors.py
wsimple/api/requestor.py
wsimple/api/tokens.py
wsimple-3.0.1.dist-info/LICENSE
wsimple-3.0.1.dist-info/METADATA
wsimple-3.0.1.dist-info/WHEEL
wsimple-3.0.1.dist-info/top_level.txt
wsimple-3.0.1.dist-info/RECORD
