Metadata-Version: 2.1
Name: wsimple
Version: 3.0.1
Summary: Wsimple.py: a API and Web interface for Wealthsimple Trade
Home-page: https://github.com/yusuf8ahmed/Wsimple
Author: Yusuf Ahmed
Author-email: yusufahmed172@gmail.com
License: UNKNOWN
Keywords: wsimple
Platform: any
Classifier: Development Status :: 3 - Alpha
Classifier: Programming Language :: Python :: 3
Classifier: License :: OSI Approved :: MIT License
Classifier: Operating System :: OS Independent
Requires-Python: >=3
